{"name":"emed","tagline":"","body":"### Elektroniczna karta pacjenta\r\nSystem zarządzania elektroniczną kartą pacjenta. Pozwala zrezygnować z prowadzenia papierowej dokumentacji medycznej i zastąpienie jej przez scenatralizowany system przechowywania danych. W skład systemu wchodzą aplikacje:\r\n\r\n- serwer usług przechowujący dane\r\n- aplikacja mobilna do codziennej pracy\r\n- aplikacja desktopowa do zarządzania całością systemu\r\n\r\n### Serwer usług REST\r\nOdpowiada za przechowywanie danych systemu. Udostępnia usługi dla aplikacji mobilnej oraz aplikacji desktopowej.\r\n\r\n### Aplikacja mobilna\r\nAplikacja do codziennej pracy pielęgniarek i lekarzy. Pozwala wprowadzać pomiary oraz ułatwia analizę przez ekrany wizualizujące historię pacjenta.\r\n\r\n![](http://glipecki.github.io/emed/images/emed-mobile/lista_pacjentow.png)\r\n![](http://glipecki.github.io/emed/images/emed-mobile/hemodynamika.png)\r\n![](http://glipecki.github.io/emed/images/emed-mobile/bilans_plynow.png)\r\n![](http://glipecki.github.io/emed/images/emed-mobile/dodaj_obserwacje_domain.png)\r\n![](http://glipecki.github.io/emed/images/emed-mobile/dodaj_obserwacje_grupy.png)\r\n\r\n### Aplikacja desktop\r\nPozwala zarządzać listą przyjętych pacjentów, ich historią wizyt i zebranych pomiarów. Umożliwia wygenerowanie karty pacjenta w formacie PDF.\r\n\r\n### Autorzy\r\n- @glipecki\r\n- @mmiedzinski","google":"UA-58664901-1","note":"Don't delete this file! It's used internally to help with page regeneration."}